streamlit_langgraph/__init__.py
streamlit_langgraph/agent.py
streamlit_langgraph/chat.py
streamlit_langgraph/version.py
streamlit_langgraph/core/__init__.py
streamlit_langgraph/core/executor/__init__.py
streamlit_langgraph/core/executor/conversation_history.py
streamlit_langgraph/core/executor/create_agent.py
streamlit_langgraph/core/executor/registry.py
streamlit_langgraph/core/executor/response_api.py
streamlit_langgraph/core/executor/workflow.py
streamlit_langgraph/core/middleware/__init__.py
streamlit_langgraph/core/middleware/hitl.py
streamlit_langgraph/core/middleware/interrupts.py
streamlit_langgraph/core/state/__init__.py
streamlit_langgraph/core/state/state_schema.py
streamlit_langgraph/core/state/state_sync.py
streamlit_langgraph/ui/__init__.py
streamlit_langgraph/ui/display_manager.py
streamlit_langgraph/ui/stream_processor.py
streamlit_langgraph/utils/__init__.py
streamlit_langgraph/utils/custom_tool.py
streamlit_langgraph/utils/file_handler.py
streamlit_langgraph/utils/mcp_tool.py
streamlit_langgraph/workflow/__init__.py
streamlit_langgraph/workflow/builder.py
streamlit_langgraph/workflow/prompts.py
streamlit_langgraph/workflow/agent_nodes/__init__.py
streamlit_langgraph/workflow/agent_nodes/factory.py
streamlit_langgraph/workflow/agent_nodes/handoff_delegation.py
streamlit_langgraph/workflow/agent_nodes/routing.py
streamlit_langgraph/workflow/agent_nodes/tool_calling_delegation.py
streamlit_langgraph/workflow/patterns/__init__.py
streamlit_langgraph/workflow/patterns/hierarchical.py
streamlit_langgraph/workflow/patterns/network.py
streamlit_langgraph/workflow/patterns/supervisor.py
streamlit_langgraph-0.2.0.dist-info/licenses/LICENSE
streamlit_langgraph-0.2.0.dist-info/METADATA
streamlit_langgraph-0.2.0.dist-info/WHEEL
streamlit_langgraph-0.2.0.dist-info/top_level.txt
streamlit_langgraph-0.2.0.dist-info/RECORD
