Metadata-Version: 2.4
Name: streamlit-langgraph
Version: 0.2.0
Summary: A Streamlit package for building multiagent web interfaces with LangGraph
Home-page: https://github.com/JjongX/streamlit-langgraph
Author: Jong Ha Shin
Author-email: shinjh1206@gmail.com
License: MIT
Keywords: streamlit langgraph multiagent ai chatbot llm
Classifier: Development Status :: 3 - Alpha
Classifier: Intended Audience :: Developers
Classifier: Programming Language :: Python :: 3
Classifier: Programming Language :: Python :: 3.10
Classifier: Programming Language :: Python :: 3.11
Classifier: Programming Language :: Python :: 3.12
Classifier: Topic :: Software Development :: Libraries :: Python Modules
Classifier: Topic :: Scientific/Engineering :: Artificial Intelligence
Requires-Python: >=3.10
License-File: LICENSE
Requires-Dist: streamlit>=1.50.0
Requires-Dist: langchain>=1.0.1
Requires-Dist: langgraph>=1.0.1
Requires-Dist: langchain-openai>=1.0.0
Requires-Dist: openai>=2.3.0
Requires-Dist: typing-extensions>=4.15.0
Requires-Dist: pyyaml>=6.0
Requires-Dist: langchain-mcp-adapters>=0.1.13
Requires-Dist: fastmcp==2.13.1
Dynamic: author
Dynamic: author-email
Dynamic: classifier
Dynamic: description
Dynamic: description-content-type
Dynamic: home-page
Dynamic: keywords
Dynamic: license
Dynamic: license-file
Dynamic: requires-dist
Dynamic: requires-python
Dynamic: summary
